README.rst
setup.py
awesome_avatar/__init__.py
awesome_avatar/fields.py
awesome_avatar/forms.py
awesome_avatar/models.py
awesome_avatar/settings.py
awesome_avatar/widgets.py
awesome_avatar/static/awesome_avatar/awesome-avatar.css
awesome_avatar/static/awesome_avatar/awesome-avatar.js
awesome_avatar/static/imgareaselect/GPL-LICENSE.txt
awesome_avatar/static/imgareaselect/MIT-LICENSE.txt
awesome_avatar/static/imgareaselect/css/border-anim-h.gif
awesome_avatar/static/imgareaselect/css/border-anim-v.gif
awesome_avatar/static/imgareaselect/css/border-h.gif
awesome_avatar/static/imgareaselect/css/border-v.gif
awesome_avatar/static/imgareaselect/css/imgareaselect-animated.css
awesome_avatar/static/imgareaselect/css/imgareaselect-default.css
awesome_avatar/static/imgareaselect/css/imgareaselect-deprecated.css
awesome_avatar/static/imgareaselect/scripts/jquery.imgareaselect.js
awesome_avatar/static/imgareaselect/scripts/jquery.imgareaselect.min.js
awesome_avatar/static/imgareaselect/scripts/jquery.imgareaselect.pack.js
awesome_avatar/static/imgareaselect/scripts/jquery.min.js
awesome_avatar/templates/awesome_avatar/widget.html
django_awesome_avatar.egg-info/PKG-INFO
django_awesome_avatar.egg-info/SOURCES.txt
django_awesome_avatar.egg-info/dependency_links.txt
django_awesome_avatar.egg-info/top_level.txt