Metadata-Version: 1.0
Name: django-awesome-avatar
Version: 1.0.7
Summary: Django Avatar field
Home-page: https://github.com/dimka665/django-awesome-avatar
Author: Dmitry Voronin
Author-email: dimka665@gmail.com
License: BSD
Platform: UNKNOWN
